qflux/__init__.py
qflux/GQME/__init__.py
qflux/GQME/dynamics_GQME.py
qflux/GQME/params.py
qflux/GQME/params_class.py
qflux/GQME/readwrite.py
qflux/GQME/tdvp.py
qflux/GQME/tt_tfd.py
qflux/GQME/tt_utils.py
qflux/closed_systems/VarQTE.py
qflux/closed_systems/__init__.py
qflux/closed_systems/classical_methods.py
qflux/closed_systems/custom_execute.py
qflux/closed_systems/direct_method.py
qflux/closed_systems/hamiltonians.py
qflux/closed_systems/qubit_methods.py
qflux/closed_systems/spin_dynamics_oo.py
qflux/closed_systems/spin_propagators.py
qflux/closed_systems/utils.py
qflux/open_systems/__init__.py
qflux/open_systems/dilation_circuit.py
qflux/open_systems/numerical_methods.py
qflux/open_systems/params.py
qflux/open_systems/quantum_simulation.py
qflux/open_systems/trans_basis.py
qflux/open_systems/walsh_gray_optimization.py
qflux/typing/__init__.py
qflux/typing/examples.py
qflux/utils/__init__.py
qflux/utils/io.py
qflux/utils/logging_config.py
qflux/variational_methods/__init__.py
qflux/variational_methods/qmad/__init__.py
qflux/variational_methods/qmad/ansatz.py
qflux/variational_methods/qmad/effh.py
qflux/variational_methods/qmad/solver.py
qflux-0.1.0.dist-info/licenses/LICENSE
qflux-0.1.0.dist-info/METADATA
qflux-0.1.0.dist-info/WHEEL
qflux-0.1.0.dist-info/top_level.txt
qflux-0.1.0.dist-info/RECORD
