Metadata-Version: 2.4
Name: qflux
Version: 0.1.0
Summary: qflux is a package for running quantum dynamics calculations on quantum devices.
Author: Saurabh Shivpuje
Author-email: Brandon Allen <brandon.allen@yale.edu>, Delmar Cabral <delmar.azevedocabral@yale.edu>, Alexander Soudackov <alexander.soudackov@yale.edu>, Xiaohan Dan <xiaohan.dan@yale.edu>, Cameron Cianci <cameron.cianci@gmail.com>, Anton Morgunov <anton@ischemist.com>
Maintainer-email: Brandon Allen <brandon.allen@yale.edu>, Delmar Cabral <delmar.azevedocabral@yale.edu>, Alexander Soudackov <alexander.soudackov@yale.edu>
License-Expression: AGPL-3.0
Project-URL: Homepage, https://github.com/batistagroup/qflux
Project-URL: Issues, https://github.com/batistagroup/qflux/issues
Project-URL: Documentation, https://qflux.batistalab.com
Keywords: Quantum Computing,chemistry,quantum dynamics
Requires-Python: >=3.10
License-File: LICENSE
Requires-Dist: requests
Requires-Dist: importlib-metadata
Requires-Dist: qiskit>=2.0.0
Requires-Dist: qiskit-aer>=0.17.0
Requires-Dist: qiskit-algorithms>=0.3.1
Requires-Dist: qiskit-ibm-runtime>=0.37.0
Requires-Dist: tomli>=2.2.1
Requires-Dist: matplotlib>=3.10
Requires-Dist: numpy>=2.0
Requires-Dist: pylatexenc>=2.10
Requires-Dist: qutip>=5.0
Requires-Dist: scipy
Requires-Dist: tqdm
Requires-Dist: graycode>=1.0.5
Requires-Dist: ipywidgets>=8.1.8
Provides-Extra: dev
Requires-Dist: ipykernel>=6.29.5; extra == "dev"
Requires-Dist: rich>=13.9.4; extra == "dev"
Requires-Dist: pre-commit>=4.1.0; extra == "dev"
Requires-Dist: ruff>=0.9.6; extra == "dev"
Requires-Dist: pytest>=8.3.4; extra == "dev"
Requires-Dist: mypy>=1.15.0; extra == "dev"
Requires-Dist: mkdocs>=1.6.1; extra == "dev"
Requires-Dist: mkdocstrings-python>=1.15.0; extra == "dev"
Requires-Dist: material-plausible-plugin>=0.3.0; extra == "dev"
Requires-Dist: mkdocs-material>=9.6.4; extra == "dev"
Requires-Dist: types-tqdm>=4.67.0.20241221; extra == "dev"
Provides-Extra: gqme
Requires-Dist: mpsqd; extra == "gqme"
Dynamic: license-file
